pyDataStore/__init__.py
pyDataStore/pydatastore.py
pyDataStore-1.0.6.dist-info/LICENSE
pyDataStore-1.0.6.dist-info/METADATA
pyDataStore-1.0.6.dist-info/WHEEL
pyDataStore-1.0.6.dist-info/top_level.txt
pyDataStore-1.0.6.dist-info/RECORD
