Metadata-Version: 2.1
Name: pyDataStore
Version: 1.0.6
Summary: Persistent and portable serialized data store.
Home-page: https://github.com/kakaiba-talaga/pyDataStore
Author: kakaiba™
Author-email: kakaiba+pypi@gmail.com
License: GPL-3.0-or-later
Keywords: datastore,data,store,portable,storage,utilities
Platform: UNKNOWN
Classifier: Development Status :: 5 - Production/Stable
Classifier: License :: OSI Approved :: GNU General Public License v3 or later (GPLv3+)
Classifier: Operating System :: OS Independent
Classifier: Programming Language :: Python :: 3.5
Classifier: Programming Language :: Python :: 3.6
Classifier: Programming Language :: Python :: 3.7
Classifier: Programming Language :: Python :: 3.8
Classifier: Programming Language :: Python :: 3.9
Classifier: Topic :: Software Development :: Libraries :: Python Modules
Classifier: Topic :: Utilities
Requires-Python: >=3.5, <3.10
License-File: LICENSE
Requires-Dist: pycryptodome (>=3.10.1)
